GPA/__init__.py
GPA/graphs.py
GPA/modules/__init__.py
GPA/modules/basic.py
GPA-0.1.0.dist-info/LICENSE
GPA-0.1.0.dist-info/METADATA
GPA-0.1.0.dist-info/WHEEL
GPA-0.1.0.dist-info/top_level.txt
GPA-0.1.0.dist-info/RECORD
