Metadata-Version: 2.1
Name: GPA
Version: 0.1.0
Summary: Python Library for Graph Program Analysis
Home-page: https://github.com/shuwang127/libgpa
Author: Shu Wang
Keywords: gpa graph program analysis
Platform: any
Classifier: Programming Language :: Python :: 3
Classifier: License :: OSI Approved :: GNU General Public License v3 (GPLv3)
Classifier: Topic :: Scientific/Engineering
Classifier: Topic :: Software Development
Classifier: Topic :: Text Processing
Classifier: Topic :: Security
License-File: LICENSE
